pybandee/AUTHORS.txt
pybandee/VERSION.txt
pybandee/__init__.py
pybandee/_utils/__init__.py
pybandee/_utils/_numba_helpers.py
pybandee/penta/__init__.py
pybandee/penta/numba/__init__.py
pybandee/penta/numba/_ptrans1.py
pybandee-0.0a2.dist-info/LICENSE
pybandee-0.0a2.dist-info/METADATA
pybandee-0.0a2.dist-info/WHEEL
pybandee-0.0a2.dist-info/top_level.txt
pybandee-0.0a2.dist-info/RECORD
