Metadata-Version: 2.2
Name: pybandee
Version: 0.0a2
Summary: A fast Python package specialised on solving banded linear systems
Author-email: Niklas Zell <nik.zoe@web.de>
License: MIT License
Keywords: python,numba,linear-algebra,banded-matrices,linear-systems,pentadiagonal-linear-systems
Requires-Python: >=3.9
License-File: LICENSE
Requires-Dist: numpy>=1.21.0
Requires-Dist: scipy>=1.7.0
Provides-Extra: dev
Requires-Dist: black>=24.4.0; extra == "dev"
Requires-Dist: build; extra == "dev"
Requires-Dist: coverage; extra == "dev"
Requires-Dist: ipympl; extra == "dev"
Requires-Dist: isort[colors]>=5.13.0; extra == "dev"
Requires-Dist: jupyter; extra == "dev"
Requires-Dist: line-profiler; extra == "dev"
Requires-Dist: matplotlib; extra == "dev"
Requires-Dist: mypy>=1.11.0; extra == "dev"
Requires-Dist: pandas>=2.2.0; extra == "dev"
Requires-Dist: perfplot; extra == "dev"
Requires-Dist: pycodestyle>=2.12.0; extra == "dev"
Requires-Dist: pyright[nodejs]>=1.1.300; extra == "dev"
Requires-Dist: pytest; extra == "dev"
Requires-Dist: pytest-cov; extra == "dev"
Requires-Dist: pytest-sugar; extra == "dev"
Requires-Dist: pytest-xdist; extra == "dev"
Requires-Dist: ruff>=0.5.0; extra == "dev"
Requires-Dist: twine; extra == "dev"
Provides-Extra: fast
Requires-Dist: numba>=0.56.0; extra == "fast"
Provides-Extra: git-ci
Requires-Dist: black>=24.4.0; extra == "git-ci"
Requires-Dist: coverage; extra == "git-ci"
Requires-Dist: isort[colors]>=5.13.0; extra == "git-ci"
Requires-Dist: mypy>=1.11.0; extra == "git-ci"
Requires-Dist: pandas>=2.2.0; extra == "git-ci"
Requires-Dist: pycodestyle>=2.12.0; extra == "git-ci"
Requires-Dist: pyright[nodejs]>=1.1.300; extra == "git-ci"
Requires-Dist: pytest; extra == "git-ci"
Requires-Dist: pytest-cov; extra == "git-ci"
Requires-Dist: pytest-sugar; extra == "git-ci"
Requires-Dist: pytest-xdist; extra == "git-ci"
Requires-Dist: ruff>=0.5.0; extra == "git-ci"
